Metadata-Version: 2.1
Name: cmdlet
Version: 0.4.2
Summary: Cmdlet provides pipe-like mechanism to cascade functions and generators.
Home-page: https://github.com/GaryLee/cmdlet
Author: Gary Lee
Author-email: garywlee@gmail.com
License: UNKNOWN
Download-URL: https://github.com/GaryLee/cmdlet/tarball/v0.4.2
Keywords: pipe,generator,iterator,sh,shell,infix,operator
Platform: UNKNOWN
Classifier: Development Status :: 4 - Beta
Classifier: Environment :: Console
Classifier: Intended Audience :: Developers
Classifier: License :: OSI Approved :: MIT License
Classifier: Operating System :: OS Independent
Classifier: Programming Language :: Python :: 2
Classifier: Programming Language :: Python :: 3
Classifier: Topic :: Utilities
Classifier: Topic :: Software Development
Classifier: Topic :: Software Development :: Libraries
Classifier: Topic :: Software Development :: Libraries :: Python Modules
